jinja2_stringcase/__init__.py
jinja2_stringcase/jinja2_stringcase.py
jinja2_stringcase-0.1.0.dist-info/METADATA
jinja2_stringcase-0.1.0.dist-info/RECORD
jinja2_stringcase-0.1.0.dist-info/WHEEL
jinja2_stringcase-0.1.0.dist-info/top_level.txt
