Metadata-Version: 2.1
Name: jinja2-stringcase
Version: 0.1.0
Summary: Jinja2 extension contains filters to convert case
Home-page: https://github.com/ufranske/jinja2_stringcase
Author: Vladimir Franskevich
Author-email: vladimir.franskevich@gmail.com
License: MIT license
Keywords: jinja2_stringcase
Platform: UNKNOWN
Classifier: Development Status :: 2 - Pre-Alpha
Classifier: Intended Audience :: Developers
Classifier: License :: OSI Approved :: MIT License
Classifier: Natural Language :: English
Classifier: Programming Language :: Python :: 2
Classifier: Programming Language :: Python :: 2.7
Classifier: Programming Language :: Python :: 3
Classifier: Programming Language :: Python :: 3.4
Classifier: Programming Language :: Python :: 3.5
Classifier: Programming Language :: Python :: 3.6
Requires-Dist: jinja2
Requires-Dist: stringcase
